voxcov-0.2.8.dist-info/METADATA
voxcov-0.2.8.dist-info/WHEEL
voxcov-0.2.8.dist-info/license_files/LICENSE
voxcov/__init__.py
voxcov/voxcov.cp38-win_amd64.pyd
voxcov-0.2.8.dist-info/RECORD
