Metadata-Version: 2.1
Name: voxcov
Version: 0.2.8
License-File: LICENSE
Author: Thomas Mulvaney <mulvaney@mailbox.org>
Author-email: Thomas Mulvaney <mulvaney@mailbox.org>
